<?xml version="1.0" encoding="UTF-8"?>

<!-- generated on 2023-06-26 17:40:46 by Eclipse SUMO GUI Version 1.17.0
<configuration xmlns:xsi="http://www.w3.org/2001/XMLSchema-instance" xsi:noNamespaceSchemaLocation="http://sumo.dlr.de/xsd/sumoConfiguration.xsd">

    <input>
        <net-file value="../nets/simple_intersection/simple_intersection.net.xml"/>
        <route-files value="../nets/simple_intersection/simple_intersection.rou.xml"/>
    </input>

    <output>
        <tripinfo-output value="../data/tripinfo.xml"/>
        <collision-output value="../data/collision.xml"/>
    </output>

    <processing>
        <collision.check-junctions value="true"/>
    </processing>

    <traci_server>
        <remote-port value="61107"/>
    </traci_server>

</configuration>
-->

<collisions xmlns:xsi="http://www.w3.org/2001/XMLSchema-instance" xsi:noNamespaceSchemaLocation="http://sumo.dlr.de/xsd/collision_file.xsd">
    <collision time="70.00" type="collision" lane="E1_0" pos="0.32" collider="se_0.2" victim="we_0.6" colliderType="vt_se" victimType="DEFAULT_VEHTYPE" colliderSpeed="5.14" victimSpeed="3.20"/>
    <collision time="169.00" type="junction" lane=":J1_0_0" pos="7.45" collider="se_0.16" victim="we_0.14" colliderType="vt_se" victimType="DEFAULT_VEHTYPE" colliderSpeed="6.19" victimSpeed="8.79"/>
    <collision time="259.00" type="junction" lane=":J1_0_0" pos="7.60" collider="se_0.28" victim="we_0.20" colliderType="vt_se" victimType="DEFAULT_VEHTYPE" colliderSpeed="6.35" victimSpeed="9.80"/>
    <collision time="344.00" type="junction" lane=":J1_0_0" pos="6.90" collider="se_0.38" victim="we_0.30" colliderType="vt_se" victimType="DEFAULT_VEHTYPE" colliderSpeed="6.77" victimSpeed="7.83"/>
    <collision time="347.00" type="collision" lane="E1_0" pos="0.92" collider="se_0.37" victim="we_0.29" colliderType="vt_se" victimType="DEFAULT_VEHTYPE" colliderSpeed="5.70" victimSpeed="9.25"/>
    <collision time="516.00" type="junction" lane=":J1_0_0" pos="7.62" collider="se_0.48" victim="we_0.43" colliderType="vt_se" victimType="DEFAULT_VEHTYPE" colliderSpeed="5.02" victimSpeed="6.03"/>
    <collision time="518.00" type="junction" lane=":J1_0_0" pos="5.35" collider="se_0.50" victim="we_0.46" colliderType="vt_se" victimType="DEFAULT_VEHTYPE" colliderSpeed="6.35" victimSpeed="7.47"/>
    <collision time="523.00" type="junction" lane=":J1_2_0" pos="10.67" collider="we_0.47" victim="se_0.54" colliderType="DEFAULT_VEHTYPE" victimType="vt_se" colliderSpeed="4.98" victimSpeed="5.58"/>
    <collision time="526.00" type="junction" lane=":J1_2_0" pos="12.38" collider="we_0.48" victim="se_0.53" colliderType="DEFAULT_VEHTYPE" victimType="vt_se" colliderSpeed="9.59" victimSpeed="6.94"/>
    <collision time="534.00" type="junction" lane=":J1_2_0" pos="13.44" collider="we_0.49" victim="se_0.55" colliderType="DEFAULT_VEHTYPE" victimType="vt_se" colliderSpeed="1.38" victimSpeed="6.20"/>
    <collision time="604.00" type="junction" lane=":J1_0_0" pos="7.24" collider="se_0.63" victim="we_0.57" colliderType="vt_se" victimType="DEFAULT_VEHTYPE" colliderSpeed="6.22" victimSpeed="6.55"/>
    <collision time="691.00" type="junction" lane=":J1_0_0" pos="5.78" collider="se_0.73" victim="we_0.68" colliderType="vt_se" victimType="DEFAULT_VEHTYPE" colliderSpeed="4.66" victimSpeed="15.07"/>
    <collision time="708.00" type="collision" lane="E1_0" pos="0.22" collider="se_0.77" victim="we_0.70" colliderType="vt_se" victimType="DEFAULT_VEHTYPE" colliderSpeed="6.91" victimSpeed="9.00"/>
    <collision time="787.00" type="junction" lane=":J1_0_0" pos="8.80" collider="se_0.86" victim="we_0.80" colliderType="vt_se" victimType="DEFAULT_VEHTYPE" colliderSpeed="5.71" victimSpeed="9.03"/>
    <collision time="965.00" type="collision" lane="E1_0" pos="2.45" collider="se_0.103" victim="we_0.93" colliderType="vt_se" victimType="DEFAULT_VEHTYPE" colliderSpeed="6.57" victimSpeed="8.66"/>
    <collision time="983.00" type="junction" lane=":J1_0_0" pos="5.47" collider="se_0.106" victim="we_0.96" colliderType="vt_se" victimType="DEFAULT_VEHTYPE" colliderSpeed="5.89" victimSpeed="13.43"/>
    <collision time="1059.00" type="junction" lane=":J1_0_0" pos="5.79" collider="se_0.115" victim="we_0.103" colliderType="vt_se" victimType="DEFAULT_VEHTYPE" colliderSpeed="5.38" victimSpeed="1.71"/>
    <collision time="1062.00" type="junction" lane=":J1_0_0" pos="6.20" collider="se_0.117" victim="we_0.102" colliderType="vt_se" victimType="DEFAULT_VEHTYPE" colliderSpeed="5.47" victimSpeed="5.31"/>
    <collision time="1144.00" type="junction" lane=":J1_0_0" pos="6.08" collider="se_0.124" victim="we_0.110" colliderType="vt_se" victimType="DEFAULT_VEHTYPE" colliderSpeed="5.26" victimSpeed="7.22"/>
    <collision time="1149.00" type="junction" lane=":J1_0_0" pos="7.45" collider="se_0.126" victim="we_0.112" colliderType="vt_se" victimType="DEFAULT_VEHTYPE" colliderSpeed="5.86" victimSpeed="7.95"/>
    <collision time="1243.00" type="collision" lane="E1_0" pos="1.18" collider="se_0.136" victim="we_0.119" colliderType="vt_se" victimType="DEFAULT_VEHTYPE" colliderSpeed="5.70" victimSpeed="6.38"/>
    <collision time="1327.00" type="junction" lane=":J1_2_0" pos="12.19" collider="we_0.132" victim="se_0.144" colliderType="DEFAULT_VEHTYPE" victimType="vt_se" colliderSpeed="1.96" victimSpeed="6.91"/>
    <collision time="1338.00" type="collision" lane="E1_0" pos="2.29" collider="se_0.147" victim="we_0.135" colliderType="vt_se" victimType="DEFAULT_VEHTYPE" colliderSpeed="6.49" victimSpeed="7.72"/>
    <collision time="1414.00" type="junction" lane=":J1_0_0" pos="6.39" collider="se_0.154" victim="we_0.143" colliderType="vt_se" victimType="DEFAULT_VEHTYPE" colliderSpeed="5.42" victimSpeed="7.48"/>
    <collision time="1509.00" type="junction" lane=":J1_0_0" pos="8.77" collider="se_0.164" victim="we_0.153" colliderType="vt_se" victimType="DEFAULT_VEHTYPE" colliderSpeed="6.16" victimSpeed="1.81"/>
    <collision time="1512.00" type="junction" lane=":J1_0_0" pos="5.91" collider="se_0.167" victim="we_0.154" colliderType="vt_se" victimType="DEFAULT_VEHTYPE" colliderSpeed="4.21" victimSpeed="5.00"/>
    <collision time="1526.00" type="collision" lane="E1_0" pos="0.83" collider="se_0.169" victim="we_0.155" colliderType="vt_se" victimType="DEFAULT_VEHTYPE" colliderSpeed="6.91" victimSpeed="9.92"/>
    <collision time="1597.00" type="junction" lane=":J1_0_0" pos="7.93" collider="se_0.175" victim="we_0.162" colliderType="vt_se" victimType="DEFAULT_VEHTYPE" colliderSpeed="5.43" victimSpeed="6.15"/>
    <collision time="1609.00" type="junction" lane=":J1_0_0" pos="8.17" collider="se_0.179" victim="we_0.163" colliderType="vt_se" victimType="DEFAULT_VEHTYPE" colliderSpeed="6.44" victimSpeed="11.60"/>
    <collision time="1691.00" type="junction" lane=":J1_2_0" pos="14.11" collider="we_0.169" victim="se_0.185" colliderType="DEFAULT_VEHTYPE" victimType="vt_se" colliderSpeed="3.71" victimSpeed="6.31"/>
    <collision time="1955.00" type="junction" lane=":J1_0_0" pos="8.09" collider="se_0.206" victim="we_0.189" colliderType="vt_se" victimType="DEFAULT_VEHTYPE" colliderSpeed="5.20" victimSpeed="3.63"/>
    <collision time="2045.00" type="collision" lane="E1_0" pos="1.20" collider="se_0.212" victim="we_0.198" colliderType="vt_se" victimType="DEFAULT_VEHTYPE" colliderSpeed="5.49" victimSpeed="5.29"/>
    <collision time="2227.00" type="junction" lane=":J1_0_0" pos="6.96" collider="se_0.227" victim="we_0.216" colliderType="vt_se" victimType="DEFAULT_VEHTYPE" colliderSpeed="5.09" victimSpeed="9.75"/>
    <collision time="2674.00" type="junction" lane=":J1_0_0" pos="7.02" collider="se_0.269" victim="we_0.259" colliderType="vt_se" victimType="DEFAULT_VEHTYPE" colliderSpeed="5.92" victimSpeed="8.18"/>
    <collision time="2767.00" type="junction" lane=":J1_2_0" pos="12.54" collider="we_0.265" victim="se_0.276" colliderType="DEFAULT_VEHTYPE" victimType="vt_se" colliderSpeed="2.38" victimSpeed="6.60"/>
    <collision time="2857.00" type="junction" lane=":J1_0_0" pos="7.02" collider="se_0.282" victim="we_0.275" colliderType="vt_se" victimType="DEFAULT_VEHTYPE" colliderSpeed="5.95" victimSpeed="7.28"/>
    <collision time="2865.00" type="junction" lane=":J1_0_0" pos="6.70" collider="se_0.286" victim="we_0.276" colliderType="vt_se" victimType="DEFAULT_VEHTYPE" colliderSpeed="5.04" victimSpeed="4.08"/>
    <collision time="3037.00" type="junction" lane=":J1_2_0" pos="14.35" collider="we_0.292" victim="se_0.304" colliderType="DEFAULT_VEHTYPE" victimType="vt_se" colliderSpeed="4.22" victimSpeed="5.96"/>
    <collision time="3042.00" type="junction" lane=":J1_0_0" pos="6.17" collider="se_0.305" victim="we_0.294" colliderType="vt_se" victimType="DEFAULT_VEHTYPE" colliderSpeed="5.76" victimSpeed="5.80"/>
    <collision time="3047.00" type="junction" lane=":J1_0_0" pos="7.75" collider="se_0.306" victim="we_0.295" colliderType="vt_se" victimType="DEFAULT_VEHTYPE" colliderSpeed="6.62" victimSpeed="8.64"/>
    <collision time="3052.00" type="junction" lane=":J1_2_0" pos="12.34" collider="we_0.296" victim="se_0.309" colliderType="DEFAULT_VEHTYPE" victimType="vt_se" colliderSpeed="3.35" victimSpeed="6.74"/>
    <collision time="3124.00" type="junction" lane=":J1_0_0" pos="5.65" collider="se_0.314" victim="we_0.299" colliderType="vt_se" victimType="DEFAULT_VEHTYPE" colliderSpeed="4.86" victimSpeed="6.22"/>
    <collision time="3127.00" type="collision" lane="E1_0" pos="0.01" collider="se_0.316" victim="we_0.300" colliderType="vt_se" victimType="DEFAULT_VEHTYPE" colliderSpeed="5.20" victimSpeed="10.12"/>
    <collision time="3219.00" type="junction" lane=":J1_0_0" pos="5.76" collider="se_0.321" victim="we_0.305" colliderType="vt_se" victimType="DEFAULT_VEHTYPE" colliderSpeed="6.84" victimSpeed="1.90"/>
    <collision time="3394.00" type="junction" lane=":J1_0_0" pos="7.21" collider="se_0.342" victim="we_0.315" colliderType="vt_se" victimType="DEFAULT_VEHTYPE" colliderSpeed="5.75" victimSpeed="8.07"/>
    <collision time="3487.00" type="junction" lane=":J1_0_0" pos="5.14" collider="se_0.350" victim="we_0.322" colliderType="vt_se" victimType="DEFAULT_VEHTYPE" colliderSpeed="6.26" victimSpeed="2.53"/>
    <collision time="3579.00" type="junction" lane=":J1_2_0" pos="13.71" collider="we_0.331" victim="se_0.356" colliderType="DEFAULT_VEHTYPE" victimType="vt_se" colliderSpeed="8.76" victimSpeed="6.97"/>
</collisions>
